[{"model": "admin.logentry", "pk": 1, "fields": {"action_time": "2022-02-26T02:08:16.480Z", "user": 1, "content_type": 16, "object_id": "ZW0001", "object_repr": "Shirt", "action_flag": 1, "change_message": "[{\"added\": {}}]"}}, {"model": "admin.logentry", "pk": 2, "fields": {"action_time": "2022-02-26T02:08:37.310Z", "user": 1, "content_type": 8, "object_id": "ZM0001", "object_repr": "VelVet meter", "action_flag": 1, "change_message": "[{\"added\": {}}]"}}, {"model": "admin.logentry", "pk": 3, "fields": {"action_time": "2022-02-26T05:58:51.381Z", "user": 1, "content_type": 9, "object_id": "ZA786", "object_repr": "ZA786 Angappan", "action_flag": 3, "change_message": ""}}, {"model": "admin.logentry", "pk": 4, "fields": {"action_time": "2022-02-26T06:09:00.959Z", "user": 1, "content_type": 9, "object_id": "ZA786", "object_repr": "ZA786 Angappan", "action_flag": 3, "change_message": ""}}, {"model": "auth.user", "pk": 1, "fields": {"password": "pbkdf2_sha256$320000$NaerKfsJmPbXdbKi8WuTEa$LtM1k7JE+cRqOUDVXnjS0166NNrtm1Bp4NnmxztMUvI=", "last_login": "2022-02-26T01:47:11.874Z", "is_superuser": true, "username": "angappanmuthu", "first_name": "", "last_name": "", "email": "", "is_staff": true, "is_active": true, "date_joined": "2022-02-26T01:46:57.125Z", "groups": [], "user_permissions": []}}, {"model": "sessions.session", "pk": "99ivxlu1k2o5qdtyf8ct3j0lvzta8frm", "fields": {"session_data": ".eJxVjEEOwiAQRe_C2hBgKB1duu8ZCMOAVA0kpV0Z765NutDtf-_9l_BhW4vfelr8zOIitDj9bhTiI9Ud8D3UW5Ox1XWZSe6KPGiXU-P0vB7u30EJvXxr5GwzZ9Bsrc6KDDgFCAMxAYRxYMuAmpwLY47oEEwkYIXOnq1Go8X7A-LYNz4:1nNmAx:qC1uV5EBTB7TUvPJ1SbsvDWBj58w0FHKFqQtpUAqoPc", "expire_date": "2022-03-12T01:47:11.875Z"}}, {"model": "api.customer", "pk": "ZC83498", "fields": {"cust_name": "Angappan", "mobile": "8825942331", "email": "sdf@a.cm", "password": "1234", "address": "asdf", "city": "sdad", "pincode": "809798"}}, {"model": "api.work", "pk": "ZW0001", "fields": {"work_name": "Shirt", "wage_type": "full", "amount": 100}}, {"model": "api.order", "pk": "ZA786", "fields": {"customer": "ZC83498", "booking_date_time": "2022-02-26T06:09:57.276Z", "due_date": "2022-02-28", "order_image": "", "material_image": "", "order_voice_inst": "", "pickup_type": "", "total_amount": 900, "advance_amount": 0, "balance_amount": 900}}, {"model": "api.orderwork", "pk": 1, "fields": {"order_id": "ZA786", "work_id": "ZW0001", "quantity": "1", "amount": 100}}, {"model": "api.orderwork", "pk": 2, "fields": {"order_id": "ZA786", "work_id": "ZW0001", "quantity": "1", "amount": 100}}, {"model": "api.orderwork", "pk": 3, "fields": {"order_id": "ZA786", "work_id": "ZW0001", "quantity": "1", "amount": 100}}, {"model": "api.orderwork", "pk": 4, "fields": {"order_id": "ZA786", "work_id": "ZW0001", "quantity": "1", "amount": 100}}, {"model": "api.orderwork", "pk": 5, "fields": {"order_id": "ZA786", "work_id": "ZW0001", "quantity": "1", "amount": 100}}, {"model": "api.orderwork", "pk": 6, "fields": {"order_id": "ZA786", "work_id": "ZW0001", "quantity": "1", "amount": 100}}, {"model": "api.orderwork", "pk": 7, "fields": {"order_id": "ZA786", "work_id": "ZW0001", "quantity": "1", "amount": 100}}, {"model": "api.orderwork", "pk": 8, "fields": {"order_id": "ZA786", "work_id": "ZW0001", "quantity": "1", "amount": 100}}, {"model": "api.orderwork", "pk": 9, "fields": {"order_id": "ZA786", "work_id": "ZW0001", "quantity": "1", "amount": 100}}, {"model": "api.orderwork", "pk": 10, "fields": {"order_id": "ZA786", "work_id": "ZW0001", "quantity": "1", "amount": 100}}, {"model": "api.orderwork", "pk": 11, "fields": {"order_id": "ZA786", "work_id": "ZW0001", "quantity": "1", "amount": 100}}, {"model": "api.orderwork", "pk": 12, "fields": {"order_id": "ZA786", "work_id": "ZW0001", "quantity": "1", "amount": 100}}, {"model": "api.orderwork", "pk": 13, "fields": {"order_id": "ZA786", "work_id": "ZW0001", "quantity": "1", "amount": 100}}, {"model": "api.orderwork", "pk": 14, "fields": {"order_id": "ZA786", "work_id": "ZW0001", "quantity": "1", "amount": 100}}, {"model": "api.orderwork", "pk": 15, "fields": {"order_id": "ZA786", "work_id": "ZW0001", "quantity": "1", "amount": 100}}, {"model": "api.orderwork", "pk": 16, "fields": {"order_id": "ZA786", "work_id": "ZW0001", "quantity": "1", "amount": 100}}, {"model": "api.orderwork", "pk": 17, "fields": {"order_id": "ZA786", "work_id": "ZW0001", "quantity": "1", "amount": 100}}, {"model": "api.orderwork", "pk": 18, "fields": {"order_id": "ZA786", "work_id": "ZW0001", "quantity": "1", "amount": 100}}, {"model": "api.orderwork", "pk": 19, "fields": {"order_id": "ZA786", "work_id": "ZW0001", "quantity": "1", "amount": 100}}, {"model": "api.orderwork", "pk": 20, "fields": {"order_id": "ZA786", "work_id": "ZW0001", "quantity": "1", "amount": 100}}, {"model": "api.orderwork", "pk": 21, "fields": {"order_id": "ZA786", "work_id": "ZW0001", "quantity": "1", "amount": 100}}, {"model": "api.orderwork", "pk": 22, "fields": {"order_id": "ZA786", "work_id": "ZW0001", "quantity": "1", "amount": 100}}, {"model": "api.orderwork", "pk": 23, "fields": {"order_id": "ZA786", "work_id": "ZW0001", "quantity": "1", "amount": 100}}, {"model": "api.orderwork", "pk": 24, "fields": {"order_id": "ZA786", "work_id": "ZW0001", "quantity": "1", "amount": 100}}, {"model": "api.orderwork", "pk": 25, "fields": {"order_id": "ZA786", "work_id": "ZW0001", "quantity": "1", "amount": 100}}, {"model": "api.orderwork", "pk": 26, "fields": {"order_id": "ZA786", "work_id": "ZW0001", "quantity": "1", "amount": 100}}, {"model": "api.orderwork", "pk": 27, "fields": {"order_id": "ZA786", "work_id": "ZW0001", "quantity": "1", "amount": 100}}, {"model": "api.orderwork", "pk": 28, "fields": {"order_id": "ZA786", "work_id": "ZW0001", "quantity": "1", "amount": 100}}, {"model": "api.orderwork", "pk": 29, "fields": {"order_id": "ZA786", "work_id": "ZW0001", "quantity": "1", "amount": 100}}, {"model": "api.orderwork", "pk": 30, "fields": {"order_id": "ZA786", "work_id": "ZW0001", "quantity": "1", "amount": 100}}, {"model": "api.orderwork", "pk": 31, "fields": {"order_id": "ZA786", "work_id": "ZW0001", "quantity": "1", "amount": 100}}, {"model": "api.orderwork", "pk": 32, "fields": {"order_id": "ZA786", "work_id": "ZW0001", "quantity": "1", "amount": 100}}, {"model": "api.orderwork", "pk": 33, "fields": {"order_id": "ZA786", "work_id": "ZW0001", "quantity": "1", "amount": 100}}, {"model": "api.orderwork", "pk": 34, "fields": {"order_id": "ZA786", "work_id": "ZW0001", "quantity": "1", "amount": 100}}, {"model": "api.orderwork", "pk": 35, "fields": {"order_id": "ZA786", "work_id": "ZW0001", "quantity": "1", "amount": 100}}, {"model": "api.orderwork", "pk": 36, "fields": {"order_id": "ZA786", "work_id": "ZW0001", "quantity": "1", "amount": 100}}, {"model": "api.orderwork", "pk": 37, "fields": {"order_id": "ZA786", "work_id": "ZW0001", "quantity": "1", "amount": 100}}, {"model": "api.orderwork", "pk": 38, "fields": {"order_id": "ZA786", "work_id": "ZW0001", "quantity": "1", "amount": 100}}, {"model": "api.orderwork", "pk": 39, "fields": {"order_id": "ZA786", "work_id": "ZW0001", "quantity": "1", "amount": 100}}, {"model": "api.orderwork", "pk": 40, "fields": {"order_id": "ZA786", "work_id": "ZW0001", "quantity": "1", "amount": 100}}, {"model": "api.orderwork", "pk": 41, "fields": {"order_id": "ZA786", "work_id": "ZW0001", "quantity": "1", "amount": 100}}, {"model": "api.orderwork", "pk": 42, "fields": {"order_id": "ZA786", "work_id": "ZW0001", "quantity": "1", "amount": 100}}, {"model": "api.orderwork", "pk": 43, "fields": {"order_id": "ZA786", "work_id": "ZW0001", "quantity": "1", "amount": 100}}, {"model": "api.orderwork", "pk": 44, "fields": {"order_id": "ZA786", "work_id": "ZW0001", "quantity": "1", "amount": 100}}, {"model": "api.orderwork", "pk": 45, "fields": {"order_id": "ZA786", "work_id": "ZW0001", "quantity": "1", "amount": 100}}, {"model": "api.ordermaterial", "pk": 1, "fields": {"order_id": "ZA786", "material_id": "ZM0001", "quantity": "1", "amount": 300}}, {"model": "api.ordermaterial", "pk": 2, "fields": {"order_id": "ZA786", "material_id": "ZM0001", "quantity": "1", "amount": 300}}, {"model": "api.ordermaterial", "pk": 3, "fields": {"order_id": "ZA786", "material_id": "ZM0001", "quantity": "1", "amount": 300}}, {"model": "api.ordermaterial", "pk": 4, "fields": {"order_id": "ZA786", "material_id": "ZM0001", "quantity": "1", "amount": 300}}, {"model": "api.ordermaterial", "pk": 5, "fields": {"order_id": "ZA786", "material_id": "ZM0001", "quantity": "1", "amount": 300}}, {"model": "api.ordermaterial", "pk": 6, "fields": {"order_id": "ZA786", "material_id": "ZM0001", "quantity": "1", "amount": 300}}, {"model": "api.ordermaterial", "pk": 7, "fields": {"order_id": "ZA786", "material_id": "ZM0001", "quantity": "1", "amount": 300}}, {"model": "api.ordermaterial", "pk": 8, "fields": {"order_id": "ZA786", "material_id": "ZM0001", "quantity": "1", "amount": 300}}, {"model": "api.ordermaterial", "pk": 9, "fields": {"order_id": "ZA786", "material_id": "ZM0001", "quantity": "1", "amount": 300}}, {"model": "api.ordermaterial", "pk": 10, "fields": {"order_id": "ZA786", "material_id": "ZM0001", "quantity": "1", "amount": 300}}, {"model": "api.ordermaterial", "pk": 11, "fields": {"order_id": "ZA786", "material_id": "ZM0001", "quantity": "1", "amount": 300}}, {"model": "api.ordermaterial", "pk": 12, "fields": {"order_id": "ZA786", "material_id": "ZM0001", "quantity": "1", "amount": 300}}, {"model": "api.ordermaterial", "pk": 13, "fields": {"order_id": "ZA786", "material_id": "ZM0001", "quantity": "1", "amount": 300}}, {"model": "api.ordermaterial", "pk": 14, "fields": {"order_id": "ZA786", "material_id": "ZM0001", "quantity": "1", "amount": 300}}, {"model": "api.ordermaterial", "pk": 15, "fields": {"order_id": "ZA786", "material_id": "ZM0001", "quantity": "1", "amount": 300}}, {"model": "api.ordermaterial", "pk": 16, "fields": {"order_id": "ZA786", "material_id": "ZM0001", "quantity": "1", "amount": 300}}, {"model": "api.ordermaterial", "pk": 17, "fields": {"order_id": "ZA786", "material_id": "ZM0001", "quantity": "1", "amount": 300}}, {"model": "api.ordermaterial", "pk": 18, "fields": {"order_id": "ZA786", "material_id": "ZM0001", "quantity": "1", "amount": 300}}, {"model": "api.ordermaterial", "pk": 19, "fields": {"order_id": "ZA786", "material_id": "ZM0001", "quantity": "1", "amount": 300}}, {"model": "api.ordermaterial", "pk": 20, "fields": {"order_id": "ZA786", "material_id": "ZM0001", "quantity": "1", "amount": 300}}, {"model": "api.ordermaterial", "pk": 21, "fields": {"order_id": "ZA786", "material_id": "ZM0001", "quantity": "1", "amount": 300}}, {"model": "api.ordermaterial", "pk": 22, "fields": {"order_id": "ZA786", "material_id": "ZM0001", "quantity": "1", "amount": 300}}, {"model": "api.ordermaterial", "pk": 23, "fields": {"order_id": "ZA786", "material_id": "ZM0001", "quantity": "1", "amount": 300}}, {"model": "api.ordermaterial", "pk": 24, "fields": {"order_id": "ZA786", "material_id": "ZM0001", "quantity": "1", "amount": 300}}, {"model": "api.ordermaterial", "pk": 25, "fields": {"order_id": "ZA786", "material_id": "ZM0001", "quantity": "1", "amount": 300}}, {"model": "api.ordermaterial", "pk": 26, "fields": {"order_id": "ZA786", "material_id": "ZM0001", "quantity": "1", "amount": 300}}, {"model": "api.material", "pk": "ZM0001", "fields": {"material_name": "VelVet", "measurement": "meter", "amount": 300}}, {"model": "api.user", "pk": 1, "fields": {"login_id": "ZC83498", "password": "1234", "mobile": "8825942331", "role": "customer"}}, {"model": "api.tmpwork", "pk": 11, "fields": {"order_id": "ZA786", "cust_id": "ZC83498", "work_id": "ZW0001", "work_name": "Shirt", "quantity": "1", "amount": 100, "total": 100}}, {"model": "api.tmpwork", "pk": 12, "fields": {"order_id": "ZA786", "cust_id": "ZC83498", "work_id": "ZW0001", "work_name": "Shirt", "quantity": "1", "amount": 100, "total": 100}}, {"model": "api.tmpwork", "pk": 13, "fields": {"order_id": "ZA786", "cust_id": "ZC83498", "work_id": "ZW0001", "work_name": "Shirt", "quantity": "1", "amount": 100, "total": 100}}, {"model": "api.tmpmaterial", "pk": 4, "fields": {"order_id": "ZA786", "cust_id": "ZC83498", "material_id": "ZM0001", "material_name": "VelVet", "quantity": "1", "amount": 300, "total": 300}}, {"model": "api.tmpmaterial", "pk": 5, "fields": {"order_id": "ZA786", "cust_id": "ZC83498", "material_id": "ZM0001", "material_name": "VelVet", "quantity": "1", "amount": 300, "total": 300}}]